Web_Templates-0.0.0a0.post3.dist-info/METADATA
Web_Templates-0.0.0a0.post3.dist-info/RECORD
Web_Templates-0.0.0a0.post3.dist-info/WHEEL
Web_Templates-0.0.0a0.post3.dist-info/entry_points.txt
Web_Templates-0.0.0a0.post3.dist-info/top_level.txt
web_templates/__meta__.py
web_templates/base.django.html
web_templates/base.html
web_templates/base.jinja.html
web_templates/base.sphinx.html
web_templates/basic/layout.html
web_templates/django/templates/skeleton.html
web_templates/django/templates/web-templates/breadcrumb.html
web_templates/django/templatetags/__init__.py
web_templates/django/templatetags/web_templates.py
web_templates/flask/templates/skeleton.html
web_templates/python/html.py
web_templates/python/abc/__init__.py
web_templates/python/abc/tag.py
web_templates/sphinx/django/__init__.py
web_templates/sphinx/django/layout.html
web_templates/sphinx/django/theme.conf
