Metadata-Version: 2.1
Name: Web-Templates
Version: 0.0.0a0.post3
Summary: Standardized templates for Python's web frameworks
Home-page: https://gitlab.com/manaikan/web-templates/
Author: Carel van Dam
Author-email: carelvdam@gmail.com
License: UNKNOWN
Platform: UNKNOWN
Classifier: Development Status :: 3 - Alpha
Classifier: Intended Audience :: Developers
Classifier: Framework :: Flask
Classifier: Framework :: Django
Classifier: Operating System :: OS Independent
Classifier: Programming Language :: Python
Classifier: Topic :: Utilities
